abs_integration_core/__init__.py
abs_integration_core/models/__init__.py
abs_integration_core/models/integration_model.py
abs_integration_core/models/subscriptions_model.py
abs_integration_core/repository/__init__.py
abs_integration_core/repository/integration_repository.py
abs_integration_core/repository/subscriptions_repository.py
abs_integration_core/schema/__init__.py
abs_integration_core/schema/common_schema.py
abs_integration_core/schema/integration_schema.py
abs_integration_core/schema/subscription_schema.py
abs_integration_core/service/__init__.py
abs_integration_core/service/base_services/__init__.py
abs_integration_core/service/base_services/base_calendar_integration_service.py
abs_integration_core/service/base_services/base_docusign_integration_service.py
abs_integration_core/service/base_services/base_google_integration_service.py
abs_integration_core/service/base_services/base_outlook_integration_service.py
abs_integration_core/service/base_services/base_service.py
abs_integration_core/service/base_services/base_sharepoint_integration_service.py
abs_integration_core/service/provider_services/__init__.py
abs_integration_core/service/provider_services/calendar_integration_service.py
abs_integration_core/service/provider_services/docusign_integration_service.py
abs_integration_core/service/provider_services/google_integration_service.py
abs_integration_core/service/provider_services/outlook_integration_service.py
abs_integration_core/service/provider_services/sharepoint_integration_service.py
abs_integration_core/service/sql_integration_service.py
abs_integration_core/service/subscription_service.py
abs_integration_core/utils/encryption.py
abs_integration_core/utils/integration_constants.py
abs_integration_core/utils/provider_service_factory.py
abs_integration_core-0.2.3.dist-info/METADATA
abs_integration_core-0.2.3.dist-info/WHEEL
abs_integration_core-0.2.3.dist-info/RECORD
